README.txt
setup.py
pyhai/__init__.py
pyhai/utils.py
pyhai.egg-info/PKG-INFO
pyhai.egg-info/SOURCES.txt
pyhai.egg-info/dependency_links.txt
pyhai.egg-info/top_level.txt
pyhai/plugins/__init__.py
pyhai/plugins/environment.py
pyhai/plugins/hostname.py
pyhai/plugins/python.py
pyhai/plugins/linux/__init__.py
pyhai/plugins/linux/disk.py
pyhai/plugins/linux/memory.py
pyhai/plugins/linux/network.py
pyhai/plugins/linux/processor.py
pyhai/plugins/linux/system.py
pyhai/plugins/linux/centos/__init__.py
pyhai/plugins/linux/centos/software.py
pyhai/plugins/linux/ubuntu/__init__.py
pyhai/plugins/linux/ubuntu/software.py
pyhai/plugins/windows/__init__.py
pyhai/plugins/windows/disk.py
pyhai/plugins/windows/memory.py
pyhai/plugins/windows/network.py
pyhai/plugins/windows/processor.py
pyhai/plugins/windows/software.py
pyhai/plugins/windows/system.py
pyhai/profilers/__init__.py
pyhai/profilers/base.py
pyhai/profilers/default.py