Metadata-Version: 1.0
Name: pyhai
Version: 0.1.3
Summary: A system profiler/auditor written in Python that supports custom plugins.
Home-page: https://bitbucket.org/marklap/pyhai
Author: pyhai@mindmind.com
Author-email: pyhai@mindmind.com
License: http://www.apache.org/licenses/LICENSE-2.0
Download-URL: https://bitbucket.org/marklap/pyhai/src/tip/src/dist/pyhai-0.1.3.tar.gz
Platform: UNKNOWN
Classifier: Development Status :: 4 - Beta
Classifier: Intended Audience :: Developers
Classifier: Intended Audience :: Information Technology
Classifier: Intended Audience :: System Administrators
Classifier: License :: OSI Approved :: Apache Software License
Classifier: Operating System :: OS Independent
Classifier: Programming Language :: Python :: 2.7
Classifier: Topic :: System :: Monitoring
Classifier: Topic :: System :: Systems Administration
Classifier: Topic :: Utilities
